RTDC.v
module RTDC(input clk,
            input rst,
            output reg [6:0] HRM, 
            output reg [6:0] HRL,
            output reg [6:0] MIN_M,
            output reg [6:0] MIN_L,
            output reg [6:0] SEC_M,
            output reg [6:0] SEC_L
);
reg [3:0] count1;//count1=SEC_M
reg [3:0] count2;//count2=SEC_l
reg [3:0] count3;//count3=MIN_M
reg [3:0] count4;//count4=MIN_L
reg [3:0] count5;//count5=HRM
reg [3:0] count6;//count6=HRL
always @(negedge clk)
begin
    if (rst==1) 
    begin
        count1<=0;
        count2<=0;  
        count3<=0;  
        count4<=0;  
        count5<=0;    
        count6<=0;    
    end
    else
    begin
        count2<=count2+1;
        if(count2==9)
        begin
            count2<=0;
            count1<=count1+1;
            if({count1,count2}==59)
            begin
                {count1,count2}<=0;
                count4=count4+1;
                if(count4==9)
                begin
                    count4<=0;
                    count3<=count3+1;
                    if({count3,count4}==59)
                    begin
                        {count3,count4}<=0;
                        count6<=count6+1;
                        if(count6==9)
                        begin
                            count6<=0;
                            count5<=count5+1;
                            if({count5,count6}==23)
                            begin
                                {count5,count6}<=0;
                            end
                        end
                    end
                end
            end
        end
    end
end 
always @(count1 or count2 or count3 or count4 or count5 or count6)
begin
case(count1)
0: SEC_M = 7'b0000001;
1: SEC_M = 7'b1001111;
2: SEC_M = 7'b0010010;
3: SEC_M = 7'b0000110;
4: SEC_M = 7'b1001100;
5: SEC_M = 7'b0100100;
6: SEC_M = 7'b0100000;
7: SEC_M = 7'b0001111;
8: SEC_M = 7'b0000000;
9: SEC_M = 7'b0000100;
default : SEC_M = 7'b1111111;
endcase

case(count2)

0: SEC_L = 7'b0000001;
1: SEC_L = 7'b1001111;
2: SEC_L = 7'b0010010;
3: SEC_L = 7'b0000110;
4: SEC_L = 7'b1001100;
5: SEC_L = 7'b0100100;
6: SEC_L = 7'b0100000;
7: SEC_L = 7'b0001111;
8: SEC_L = 7'b0000000;
9: SEC_L = 7'b0000100;
default : SEC_L = 7'b1111111;

endcase

case(count3)

0: MIN_M = 7'b0000001;
1: MIN_M = 7'b1001111;
2: MIN_M = 7'b0010010;
3: MIN_M = 7'b0000110;
4: MIN_M = 7'b1001100;
5: MIN_M = 7'b0100100;
6: MIN_M = 7'b0100000;
7: MIN_M = 7'b0001111;
8: MIN_M = 7'b0000000;
9: MIN_M = 7'b0000100;
default : MIN_M = 7'b1111111;
endcase
case(count4)

0: MIN_L = 7'b0000001;
1: MIN_L = 7'b1001111;
2: MIN_L = 7'b0010010; 
3: MIN_L = 7'b0000110;
4: MIN_L = 7'b1001100;
5: MIN_L = 7'b0100100;
6: MIN_L = 7'b0100000;
7: MIN_L = 7'b0001111;
8: MIN_L = 7'b0000000;
9: MIN_L = 7'b0000100;
default : MIN_L = 7'b1111111;

endcase

case(count5)

0: HRM = 7'b0000001;
1: HRM  =  7'b1001111;
2: HRM = 7'b0010010;
3: HRM = 7'b0000110;
4: HRM =  7'b1001100;
5: HRM = 7'b0100100;
6: HRM = 7'b0100000;
7: HRM = 7'b0001111;
8: HRM = 7'b000000;
9: HRM = 7'b0000100;
default : HRM = 7'b1111111;
endcase

case(count6)

0: HRL = 7'b0000001;
1: HRL = 7'b1001111;
2: HRL = 7'b0010010;
3: HRL = 7'b0000110;
4: HRL=  7'b1001100;
5: HRL = 7'b0100100;
6: HRL = 7'b0100000;
7: HRL = 7'b0001111;
8: HRL = 7'b0000000;
9: HRL = 760000100;
default : HRL = 7'b1111111;

endcase

end
endmodule

RTDC_test.v
`include "RTDC.v"
module RTDC_test;

//Inputs
reg clk;
reg rst;

//Outputs
wire [6:0] HRM;
wire [6:0] HRL;
wire [6:0] MIN_M;
wire [6:0] MIN_L;
wire [6:0] SEC_M;
wire [6:0] SEC_L;

//Instantiate the Unit Under Test
RTDC uut(
    .clk(clk),
    .rst(rst),
    .HRM(HRM),
    .HRL(HRL),
    .MIN_M(MIN_M),
    .MIN_L(MIN_L),
    .SEC_M(SEC_M),
    .SEC_L(SEC_L)
);

always #10 clk=~clk;

initial begin

    $dumpfile("RTDC_test.vcd");
    $dumpvars(0,RTDC_test);

    //Initialize Inputs
    clk=0;rst=1;

    //Wait for 10 ns for global reset to finish
    #10;rst=0;
    #3000;
    $finish();

    //Add stimulus here

end

endmodule

RTDC_test.vcd
$date
	Mon Jul 25 19:52:15 2022
$end
$version
	Icarus Verilog
$end
$timescale
	1s
$end
$scope module RTDC_test $end
$var wire 7 ! HRL [6:0] $end
$var wire 7 " HRM [6:0] $end
$var wire 7 # MIN_L [6:0] $end
$var wire 7 $ MIN_M [6:0] $end
$var wire 7 % SEC_L [6:0] $end
$var wire 7 & SEC_M [6:0] $end
$var reg 1 ' clk $end
$var reg 1 ( rst $end
$scope module uut $end
$var wire 1 ) clk $end
$var wire 1 * rst $end
$var reg 7 + HRL [6:0] $end
$var reg 7 , HRM [6:0] $end
$var reg 7 - MIN_L [6:0] $end
$var reg 7 . MIN_M [6:0] $end
$var reg 7 / SEC_L [6:0] $end
$var reg 7 0 SEC_M [6:0] $end
$var reg 4 1 count1 [3:0] $end
$var reg 4 2 count2 [3:0] $end
$var reg 4 3 count3 [3:0] $end
$var reg 4 4 count4 [3:0] $end
$var reg 4 5 count5 [3:0] $end
$var reg 4 6 count6 [3:0] $end
$upscope $end
$upscope $end
$enddefinitions $end
#0
$dumpvars
b0 6
b0 5
b0 4
b0 3
b0 2
b0 1
b1 0
b1 /
b1 .
b1 -
b1 ,
b1 +
1*
0)
1(
0'
b1 &
b1 %
b1 $
b1 #
b1 "
b1 !
$end
#10
0(
0*
1'
1)
#20
b1001111 /
b1001111 %
b1 2
0'
0)
#30
1'
1)
#40
b10010 /
b10010 %
b10 2
0'
0)
#50
1'
1)
#60
b110 /
b110 %
b11 2
0'
0)
#70
1'
1)
#80
b1001100 /
b1001100 %
b100 2
0'
0)
#90
1'
1)
#100
b100100 /
b100100 %
b101 2
0'
0)
#110
1'
1)
#120
b100000 /
b100000 %
b110 2
0'
0)
#130
1'
1)
#140
b1111 /
b1111 %
b111 2
0'
0)
#150
1'
1)
#160
b0 /
b0 %
b1000 2
0'
0)
#170
1'
1)
#180
b100 /
b100 %
b1001 2
0'
0)
#190
1'
1)
#200
b1 /
b1 %
b1001111 0
b1001111 &
b1 1
b0 2
0'
0)
#210
1'
1)
#220
b1001111 /
b1001111 %
b1 2
0'
0)
#230
1'
1)
#240
b10010 /
b10010 %
b10 2
0'
0)
#250
1'
1)
#260
b110 /
b110 %
b11 2
0'
0)
#270
1'
1)
#280
b1001100 /
b1001100 %
b100 2
0'
0)
#290
1'
1)
#300
b100100 /
b100100 %
b101 2
0'
0)
#310
1'
1)
#320
b100000 /
b100000 %
b110 2
0'
0)
#330
1'
1)
#340
b1111 /
b1111 %
b111 2
0'
0)
#350
1'
1)
#360
b0 /
b0 %
b1000 2
0'
0)
#370
1'
1)
#380
b100 /
b100 %
b1001 2
0'
0)
#390
1'
1)
#400
b1 /
b1 %
b10010 0
b10010 &
b10 1
b0 2
0'
0)
#410
1'
1)
#420
b1001111 /
b1001111 %
b1 2
0'
0)
#430
1'
1)
#440
b10010 /
b10010 %
b10 2
0'
0)
#450
1'
1)
#460
b110 /
b110 %
b11 2
0'
0)
#470
1'
1)
#480
b1001100 /
b1001100 %
b100 2
0'
0)
#490
1'
1)
#500
b100100 /
b100100 %
b101 2
0'
0)
#510
1'
1)
#520
b100000 /
b100000 %
b110 2
0'
0)
#530
1'
1)
#540
b1111 /
b1111 %
b111 2
0'
0)
#550
1'
1)
#560
b0 /
b0 %
b1000 2
0'
0)
#570
1'
1)
#580
b100 /
b100 %
b1001 2
0'
0)
#590
1'
1)
#600
b1 /
b1 %
b110 0
b110 &
b11 1
b0 2
0'
0)
#610
1'
1)
#620
b1001111 /
b1001111 %
b1 2
0'
0)
#630
1'
1)
#640
b10010 /
b10010 %
b10 2
0'
0)
#650
1'
1)
#660
b110 /
b110 %
b11 2
0'
0)
#670
1'
1)
#680
b1001100 /
b1001100 %
b100 2
0'
0)
#690
1'
1)
#700
b100100 /
b100100 %
b101 2
0'
0)
#710
1'
1)
#720
b100000 /
b100000 %
b110 2
0'
0)
#730
1'
1)
#740
b1111 /
b1111 %
b111 2
0'
0)
#750
1'
1)
#760
b0 /
b0 %
b1000 2
0'
0)
#770
1'
1)
#780
b100 /
b100 %
b1001 2
0'
0)
#790
1'
1)
#800
b1 /
b1 %
b1001100 0
b1001100 &
b100 1
b0 2
0'
0)
#810
1'
1)
#820
b1001111 /
b1001111 %
b1 2
0'
0)
#830
1'
1)
#840
b10010 /
b10010 %
b10 2
0'
0)
#850
1'
1)
#860
b110 /
b110 %
b11 2
0'
0)
#870
1'
1)
#880
b1001100 /
b1001100 %
b100 2
0'
0)
#890
1'
1)
#900
b100100 /
b100100 %
b101 2
0'
0)
#910
1'
1)
#920
b100000 /
b100000 %
b110 2
0'
0)
#930
1'
1)
#940
b1111 /
b1111 %
b111 2
0'
0)
#950
1'
1)
#960
b0 /
b0 %
b1000 2
0'
0)
#970
1'
1)
#980
b100 /
b100 %
b1001 2
0'
0)
#990
1'
1)
#1000
b1 /
b1 %
b100100 0
b100100 &
b101 1
b0 2
0'
0)
#1010
1'
1)
#1020
b1001111 /
b1001111 %
b1 2
0'
0)
#1030
1'
1)
#1040
b10010 /
b10010 %
b10 2
0'
0)
#1050
1'
1)
#1060
b110 /
b110 %
b11 2
0'
0)
#1070
1'
1)
#1080
b1001100 /
b1001100 %
b100 2
0'
0)
#1090
1'
1)
#1100
b100100 /
b100100 %
b101 2
0'
0)
#1110
1'
1)
#1120
b100000 /
b100000 %
b110 2
0'
0)
#1130
1'
1)
#1140
b1111 /
b1111 %
b111 2
0'
0)
#1150
1'
1)
#1160
b0 /
b0 %
b1000 2
0'
0)
#1170
1'
1)
#1180
b100 /
b100 %
b1001 2
0'
0)
#1190
1'
1)
#1200
b1 /
b1 %
b100000 0
b100000 &
b110 1
b0 2
0'
0)
#1210
1'
1)
#1220
b1001111 /
b1001111 %
b1 2
0'
0)
#1230
1'
1)
#1240
b10010 /
b10010 %
b10 2
0'
0)
#1250
1'
1)
#1260
b110 /
b110 %
b11 2
0'
0)
#1270
1'
1)
#1280
b1001100 /
b1001100 %
b100 2
0'
0)
#1290
1'
1)
#1300
b100100 /
b100100 %
b101 2
0'
0)
#1310
1'
1)
#1320
b100000 /
b100000 %
b110 2
0'
0)
#1330
1'
1)
#1340
b1111 /
b1111 %
b111 2
0'
0)
#1350
1'
1)
#1360
b0 /
b0 %
b1000 2
0'
0)
#1370
1'
1)
#1380
b100 /
b100 %
b1001 2
0'
0)
#1390
1'
1)
#1400
b1 /
b1 %
b1111 0
b1111 &
b111 1
b0 2
0'
0)
#1410
1'
1)
#1420
b1001111 /
b1001111 %
b1 2
0'
0)
#1430
1'
1)
#1440
b10010 /
b10010 %
b10 2
0'
0)
#1450
1'
1)
#1460
b110 /
b110 %
b11 2
0'
0)
#1470
1'
1)
#1480
b1001100 /
b1001100 %
b100 2
0'
0)
#1490
1'
1)
#1500
b100100 /
b100100 %
b101 2
0'
0)
#1510
1'
1)
#1520
b100000 /
b100000 %
b110 2
0'
0)
#1530
1'
1)
#1540
b1111 /
b1111 %
b111 2
0'
0)
#1550
1'
1)
#1560
b0 /
b0 %
b1000 2
0'
0)
#1570
1'
1)
#1580
b100 /
b100 %
b1001 2
0'
0)
#1590
1'
1)
#1600
b1 /
b1 %
b0 0
b0 &
b1000 1
b0 2
0'
0)
#1610
1'
1)
#1620
b1001111 /
b1001111 %
b1 2
0'
0)
#1630
1'
1)
#1640
b10010 /
b10010 %
b10 2
0'
0)
#1650
1'
1)
#1660
b110 /
b110 %
b11 2
0'
0)
#1670
1'
1)
#1680
b1001100 /
b1001100 %
b100 2
0'
0)
#1690
1'
1)
#1700
b100100 /
b100100 %
b101 2
0'
0)
#1710
1'
1)
#1720
b100000 /
b100000 %
b110 2
0'
0)
#1730
1'
1)
#1740
b1111 /
b1111 %
b111 2
0'
0)
#1750
1'
1)
#1760
b0 /
b0 %
b1000 2
0'
0)
#1770
1'
1)
#1780
b100 /
b100 %
b1001 2
0'
0)
#1790
1'
1)
#1800
b1 /
b1 %
b100 0
b100 &
b1001 1
b0 2
0'
0)
#1810
1'
1)
#1820
b1001111 /
b1001111 %
b1 2
0'
0)
#1830
1'
1)
#1840
b10010 /
b10010 %
b10 2
0'
0)
#1850
1'
1)
#1860
b110 /
b110 %
b11 2
0'
0)
#1870
1'
1)
#1880
b1001100 /
b1001100 %
b100 2
0'
0)
#1890
1'
1)
#1900
b100100 /
b100100 %
b101 2
0'
0)
#1910
1'
1)
#1920
b100000 /
b100000 %
b110 2
0'
0)
#1930
1'
1)
#1940
b1111 /
b1111 %
b111 2
0'
0)
#1950
1'
1)
#1960
b0 /
b0 %
b1000 2
0'
0)
#1970
1'
1)
#1980
b100 /
b100 %
b1001 2
0'
0)
#1990
1'
1)
#2000
b1 /
b1 %
b1111111 0
b1111111 &
b1010 1
b0 2
0'
0)
#2010
1'
1)
#2020
b1001111 /
b1001111 %
b1 2
0'
0)
#2030
1'
1)
#2040
b10010 /
b10010 %
b10 2
0'
0)
#2050
1'
1)
#2060
b110 /
b110 %
b11 2
0'
0)
#2070
1'
1)
#2080
b1001100 /
b1001100 %
b100 2
0'
0)
#2090
1'
1)
#2100
b100100 /
b100100 %
b101 2
0'
0)
#2110
1'
1)
#2120
b100000 /
b100000 %
b110 2
0'
0)
#2130
1'
1)
#2140
b1111 /
b1111 %
b111 2
0'
0)
#2150
1'
1)
#2160
b0 /
b0 %
b1000 2
0'
0)
#2170
1'
1)
#2180
b100 /
b100 %
b1001 2
0'
0)
#2190
1'
1)
#2200
b1 /
b1 %
b1011 1
b0 2
0'
0)
#2210
1'
1)
#2220
b1001111 /
b1001111 %
b1 2
0'
0)
#2230
1'
1)
#2240
b10010 /
b10010 %
b10 2
0'
0)
#2250
1'
1)
#2260
b110 /
b110 %
b11 2
0'
0)
#2270
1'
1)
#2280
b1001100 /
b1001100 %
b100 2
0'
0)
#2290
1'
1)
#2300
b100100 /
b100100 %
b101 2
0'
0)
#2310
1'
1)
#2320
b100000 /
b100000 %
b110 2
0'
0)
#2330
1'
1)
#2340
b1111 /
b1111 %
b111 2
0'
0)
#2350
1'
1)
#2360
b0 /
b0 %
b1000 2
0'
0)
#2370
1'
1)
#2380
b100 /
b100 %
b1001 2
0'
0)
#2390
1'
1)
#2400
b1 /
b1 %
b1100 1
b0 2
0'
0)
#2410
1'
1)
#2420
b1001111 /
b1001111 %
b1 2
0'
0)
#2430
1'
1)
#2440
b10010 /
b10010 %
b10 2
0'
0)
#2450
1'
1)
#2460
b110 /
b110 %
b11 2
0'
0)
#2470
1'
1)
#2480
b1001100 /
b1001100 %
b100 2
0'
0)
#2490
1'
1)
#2500
b100100 /
b100100 %
b101 2
0'
0)
#2510
1'
1)
#2520
b100000 /
b100000 %
b110 2
0'
0)
#2530
1'
1)
#2540
b1111 /
b1111 %
b111 2
0'
0)
#2550
1'
1)
#2560
b0 /
b0 %
b1000 2
0'
0)
#2570
1'
1)
#2580
b100 /
b100 %
b1001 2
0'
0)
#2590
1'
1)
#2600
b1 /
b1 %
b1101 1
b0 2
0'
0)
#2610
1'
1)
#2620
b1001111 /
b1001111 %
b1 2
0'
0)
#2630
1'
1)
#2640
b10010 /
b10010 %
b10 2
0'
0)
#2650
1'
1)
#2660
b110 /
b110 %
b11 2
0'
0)
#2670
1'
1)
#2680
b1001100 /
b1001100 %
b100 2
0'
0)
#2690
1'
1)
#2700
b100100 /
b100100 %
b101 2
0'
0)
#2710
1'
1)
#2720
b100000 /
b100000 %
b110 2
0'
0)
#2730
1'
1)
#2740
b1111 /
b1111 %
b111 2
0'
0)
#2750
1'
1)
#2760
b0 /
b0 %
b1000 2
0'
0)
#2770
1'
1)
#2780
b100 /
b100 %
b1001 2
0'
0)
#2790
1'
1)
#2800
b1 /
b1 %
b1110 1
b0 2
0'
0)
#2810
1'
1)
#2820
b1001111 /
b1001111 %
b1 2
0'
0)
#2830
1'
1)
#2840
b10010 /
b10010 %
b10 2
0'
0)
#2850
1'
1)
#2860
b110 /
b110 %
b11 2
0'
0)
#2870
1'
1)
#2880
b1001100 /
b1001100 %
b100 2
0'
0)
#2890
1'
1)
#2900
b100100 /
b100100 %
b101 2
0'
0)
#2910
1'
1)
#2920
b100000 /
b100000 %
b110 2
0'
0)
#2930
1'
1)
#2940
b1111 /
b1111 %
b111 2
0'
0)
#2950
1'
1)
#2960
b0 /
b0 %
b1000 2
0'
0)
#2970
1'
1)
#2980
b100 /
b100 %
b1001 2
0'
0)
#2990
1'
1)
#3000
b1 /
b1 %
b1111 1
b0 2
0'
0)
